tensorcross/__init__.py
tensorcross/_types.py
tensorcross/version.py
tensorcross/model_selection/__init__.py
tensorcross/model_selection/search.py
tensorcross/model_selection/search_cv.py
tensorcross/utils/__init__.py
tensorcross/utils/dataset.py
tensorcross-1.0.0.dist-info/LICENSE
tensorcross-1.0.0.dist-info/METADATA
tensorcross-1.0.0.dist-info/WHEEL
tensorcross-1.0.0.dist-info/top_level.txt
tensorcross-1.0.0.dist-info/RECORD
