Metadata-Version: 2.1
Name: tensorcross
Version: 1.0.0
Summary: Cross Validation, Grid Search and Random Search for TensorFlow Datasets.
Author: Jan Schaffranek, Saif Al-Dilaimi
License: MIT
Classifier: License :: OSI Approved :: MIT License
Requires-Dist: keras >=2.8
Requires-Dist: numpy
Requires-Dist: scipy
Requires-Dist: scikit-learn >=1.0
